django_meili/__init__.py
django_meili/_client.py
django_meili/_settings.py
django_meili/apps.py
django_meili/models.py
django_meili/querysets.py
django_meili/tests.py
django_meili/management/__init__.py
django_meili/management/commands/__init__.py
django_meili/management/commands/clearindex.py
django_meili/management/commands/syncindex.py
django_meili/migrations/__init__.py
django_meili-0.0.12.dist-info/licenses/LICENSE
django_meili-0.0.12.dist-info/WHEEL
django_meili-0.0.12.dist-info/METADATA
django_meili-0.0.12.dist-info/RECORD
