Metadata-Version: 2.4
Name: django-meili
Version: 0.0.12
Summary: Custom Django integration for MeiliSearch.
Author-email: Ian Kollipara <ian.kollipara@cune.edu>
Requires-Python: >=3.11,<3.14
Classifier: Programming Language :: Python :: 3
Classifier: License :: OSI Approved :: MIT License
Classifier: Operating System :: OS Independent
License-File: LICENSE
Requires-Dist: django
Requires-Dist: meilisearch
Requires-Dist: djp ; extra == "djp"
Project-URL: Bug Tracker, https://github.com/ikollipara/django-meili/issues
Project-URL: Homepage, https://github.com/ikollipara/django-meili
Provides-Extra: djp
